Workbook

Sheet Performance LD
A1: In Class Case Study Model
A3: Technology | C3: Wind Energy Turbine
A5: Capacity | C5: =+'[1]Base Data'!D5 -> MW | E5: 72
A6: Capacity Factor: Note 2 | C6: =+'[1]Base Data'!D15 -> % | E6: =VLOOKUP('Performance LD'!A6,Table1[#All],8,FALSE) -> 0.4
A7: Annual Production | C7: MWH | E7: =+E5*8760*E6 -> 252288
A8: Heat Rate/Fuel Rate | C8: btu/kwh | E8: =VLOOKUP('Performance LD'!A8,Table1[#All],8,FALSE) -> 0
A9: Fixed O&M | C9: $/kw/yr | E9: =VLOOKUP('Performance LD'!A9,Table1[#All],8,FALSE) -> 42
A10: Variable O&M | C10: $/mwh | E10: =VLOOKUP('Performance LD'!A10,Table1[#All],8,FALSE) -> 0
A11: Capital Cost: Note 1 | C11: =+'[1]Base Data'!D6 -> $/kw | E11: =VLOOKUP('Performance LD'!A11,Table1[#All],8,FALSE) -> 1500
A12: EPC Capital Cost* | C12: $mm | E12: =+E5*E11*1000/1000000 -> 108
A13: Construction Debt Term | C13: Yrs | E13: =VLOOKUP('Performance LD'!A13,Table1[#All],8,FALSE) -> 3
A14: S Curve for EPC Capital Cost* | C14: Yr | E14: Y1 | F14: Yr2 | G14: Yr3
A15: S Curve for EPC Capital Cost* | C15: % | E15: 0.1 | F15: 0.4 | G15: 0.5
A16: S Curve for EPC Capital Cost* | C16: $mm | E16: =+E12*E15 -> 10.8 | F16: =+E12*F15 -> 43.2 | G16: =+E12*G15 -> 54
A17: Cost Inflation Rate | C17: % | E17: =VLOOKUP('Performance LD'!A17,Table1[#All],8,FALSE) -> 0.025
A18: Economic Life | C18: Years | E18: =VLOOKUP('Performance LD'!A18,Table1[#All],8,FALSE) -> 25
A19: Tax Rate | C19: Federal | E19: =VLOOKUP('Performance LD'!A19,Table1[#All],8,FALSE) -> 0.21
A20: Tax Depreciation | C20: MACRS | E20: =VLOOKUP('Performance LD'!A20,Table1[#All],8,FALSE) -> 5 | H20: Year 1 | I20: Year 2 | J20: Year 3 | K20: Year 4 | L20: Year 5 | M20: Year 6
A21: Tax Depreciation Rate | C21: % | H21: 0.2 | I21: 0.32 | J21: 0.192 | K21: 0.1152 | L21: 0.1152 | M21: 0.0576
A22: CO2 Emissions | C22: lbs/mmbtu | E22: 0
A23: Potential Carbon Tax | C23: $/ton | E23: 0
A25: *Excludes any development fee or interest during construction
A28: Development Fee Bonus
A30: Development Fee Bonus | C30: % EPC Capital Cost | E30: 0.05
A31: Development Fee Bonus | C31: $mm | E31: =+E30*E12 -> 5.4
A32: Capital Cost Including Development Fee | E32: =+E12+E31 -> 113.4
A33: S Curve for Total Capital Cost** | C33: Yr | E33: Yr1 | F33: Yr2 | G33: Yr3
A34: S Curve for Total Capital Cost** | C34: % | E34: 0.1 | F34: 0.4 | G34: 0.5
A35: S Curve for Total Capital Cost** | C35: $mm | E35: =+E34*$E$32 -> 11.34 | F35: =+F34*$E$32 -> 45.36 | G35: =+G34*$E$32 -> 56.7
A37: **Includes development fee but excludes interest during construction
A40: Construction Finance and Take Out Finance
A42: Construction Debt Term | C42: Yrs | E42: 3
A43: Construction Debt Rate | C43: % | E43: 0.05
A44: Construction Debt Leverage | C44: % | E44: 0.5
A46: Take-Out Debt Term | C46: Yrs | E46: 15
A47: Take-Out Debt Rate | C47: % | E47: 0.065
A48: Take-Out Debt Leverage | C48: % | E48: 0.59555421
A50: Take Out Debt is to be structrued with a mortgage style amortization with
A51: equal debt service amounts over the entire take-out term of 15 years
A53: In addition to the capital cost from the EPC contract and the Development Fee Bonus
A54: fund a 6 month debt service reserve and six months
A55: of estimated start up costs along with the final construction finance payments
A58: Fuel Contract with NatGas Co
A60: Base Price in 2025 | C60: $/mmbtu | E60: 0
A61: Fuel Price Escalator | C61: % | E61: 0
A63: Off-Take Agreement with Ready Kilowatt Power Co. | E63: Initial Offer | G63: Response
A65: Base Price in 2025 | C65: $/MWH | E65: 35 | G65: 72.235087
A66: Fuel Price Escalator | C66: % | E66: 0 | G66: 0
A69: Project Finanacial and Operating Plan
A71: Income Statement | E71: 2025 | F71: =+E71+1 -> 2026 | G71: =+F71+1 -> 2027 | H71: =+G71+1 -> 2028 | I71: =+H71+1 -> 2029 | J71: =+I71+1 -> 2030 | K71: =+J71+1 -> 2031 | L71: =+K71+1 -> 2032 | M71: =+L71+1 -> 2033 | N71: 2034 | O71: =+N71+1 -> 2035 | P71: 2036 | Q71: 2037 | R71: 2038 | S71: =+R71+1 -> 2039 | T71: =+S71+1 -> 2040 | U71: =+T71+1 -> 2041 | V71: 2039 | W71: =+V71+1 -> 2040 | X71: =+W71+1 -> 2041 | Y71: =+X71+1 -> 2042 | Z71: 2040 | AA71: =+Z71+1 -> 2041 | AB71: =+AA71+1 -> 2042 | AC71: =+AB71+1 -> 2043 | AD71: 2041 | AE71: =+AD71+1 -> 2042 | AF71: =+AE71+1 -> 2043
A73: Project Year | H73: 1 | I73: =+H73+1 -> 2 | J73: =+I73+1 -> 3 | K73: =+J73+1 -> 4 | L73: =+K73+1 -> 5 | M73: =+L73+1 -> 6 | N73: =+M73+1 -> 7 | O73: =+N73+1 -> 8 | P73: =+O73+1 -> 9 | ... AF73: =+AE73+1 -> 25
A74: Construction Year | E74: 1 | F74: 2 | G74: 3
A76: Revenues
A77: Production | C77: MWH | H77: =+$E$7 -> 252288 | I77: =+$E$7 -> 252288 | J77: =+$E$7 -> 252288 | K77: =+$E$7 -> 252288 | L77: =+$E$7 -> 252288 | M77: =+$E$7 -> 252288 | N77: =+$E$7 -> 252288 | O77: =+$E$7 -> 252288 | ... AF77: =+$E$7 -> 252288
A78: Price | C78: $/MWH | E78: =+G65 -> 72.235087 | F78: =E78*1.025 -> 74.040964 | G78: =F78*1.025 -> 75.891988 | H78: =G78*1.025 -> 77.789288 | I78: =H78*1.025 -> 79.73402 | J78: =I78*1.025 -> 81.72737 | K78: =J78*1.025 -> 83.770555 | L78: =K78*1.025 -> 85.864818 | M78: =L78*1.025 -> 88.011439 | ... AF78: =AE78*1.025 -> 140.6995
A79: Total Revenues | C79: $mm | H79: =+H77*H78/1000000 -> 19.625304 | I79: =+I77*I78/1000000 -> 20.115936 | J79: =+J77*J78/1000000 -> 20.618835 | K79: =+K77*K78/1000000 -> 21.134306 | L79: =+L77*L78/1000000 -> 21.662663 | M79: =+M77*M78/1000000 -> 22.20423 | N79: =+N77*N78/1000000 -> 22.759336 | O79: =+O77*O78/1000000 -> 23.328319 | ... AF79: =+AF77*AF78/1000000 -> 35.496796
A81: Expense
A82: Fixed O&M | C82: $/kw | E82: =+E9 -> 42 | F82: =+E82*(1+$E$17) -> 43.05 | G82: =+F82*(1+$E$17) -> 44.12625 | H82: =+G82*(1+$E$17) -> 45.229406 | I82: =+H82*(1+$E$17) -> 46.360141 | J82: =+I82*(1+$E$17) -> 47.519145 | K82: =+J82*(1+$E$17) -> 48.707124 | L82: =+K82*(1+$E$17) -> 49.924802 | M82: =+L82*(1+$E$17) -> 51.172922 | ... AF82: =+AE82*(1+$E$17) -> 81.807601
A83: Fixed O&M | C83: $mm | H83: =+H82*$E$5*1000/1000000 -> 3.2565172 | I83: =+I82*$E$5*1000/1000000 -> 3.3379302 | J83: =+J82*$E$5*1000/1000000 -> 3.4213784 | K83: =+K82*$E$5*1000/1000000 -> 3.5069129 | L83: =+L82*$E$5*1000/1000000 -> 3.5945857 | M83: =+M82*$E$5*1000/1000000 -> 3.6844504 | N83: =+N82*$E$5*1000/1000000 -> 3.7765616 | O83: =+O82*$E$5*1000/1000000 -> 3.8709757 | ... AF83: =+AF82*$E$5*1000/1000000 -> 5.8901473
A84: Variable O&M | C84: $/MWH | E84: =+E10 -> 0 | F84: =+E84*(1+$E$17) -> 0 | G84: =+F84*(1+$E$17) -> 0 | H84: =+G84*(1+$E$17) -> 0 | I84: =+H84*(1+$E$17) -> 0 | J84: =+I84*(1+$E$17) -> 0 | K84: =+J84*(1+$E$17) -> 0 | L84: =+K84*(1+$E$17) -> 0 | M84: =+L84*(1+$E$17) -> 0
A85: Variable O&M | C85: $mm | H85: =+H77*H84/1000000 -> 0 | I85: =+I77*I84/1000000 -> 0 | J85: =+J77*J84/1000000 -> 0 | K85: =+K77*K84/1000000 -> 0 | L85: =+L77*L84/1000000 -> 0 | M85: =+M77*M84/1000000 -> 0
A86: Heat Rate | C86: btu/kwh | H86: =+$E$8 -> 0 | I86: =+$E$8 -> 0 | J86: =+$E$8 -> 0 | K86: =+$E$8 -> 0 | L86: =+$E$8 -> 0 | M86: =+$E$8 -> 0
A87: Fuel Requirment | C87: mmbtus | H87: =+H86*H77*1000/1000000 -> 0 | I87: =+I86*I77*1000/1000000 -> 0 | J87: =+J86*J77*1000/1000000 -> 0 | K87: =+K86*K77*1000/1000000 -> 0 | L87: =+L86*L77*1000/1000000 -> 0 | M87: =+M86*M77*1000/1000000 -> 0
A88: Fuel price | C88: $/mmbtu | E88: =+E60 -> 0 | F88: =+E88*(1+$E$61) -> 0 | G88: =+F88*(1+$E$61) -> 0 | H88: =+G88*(1+$E$61) -> 0 | I88: =+H88*(1+$E$61) -> 0 | J88: =+I88*(1+$E$61) -> 0 | K88: =+J88*(1+$E$61) -> 0 | L88: =+K88*(1+$E$61) -> 0 | M88: =+L88*(1+$E$61) -> 0
A89: Fuel Cost | C89: $mm | H89: =+H87*H88/1000000 -> 0 | I89: =+I87*I88/1000000 -> 0 | J89: =+J87*J88/1000000 -> 0 | K89: =+K87*K88/1000000 -> 0 | L89: =+L87*L88/1000000 -> 0 | M89: =+M87*M88/1000000 -> 0
A90: Total Expense | C90: $mm | H90: =+H83+H85+H89 -> 3.2565172 | I90: =+I83+I85+I89 -> 3.3379302 | J90: =+J83+J85+J89 -> 3.4213784 | K90: =+K83+K85+K89 -> 3.5069129 | L90: =+L83+L85+L89 -> 3.5945857 | M90: =+M83+M85+M89 -> 3.6844504 | N90: =+N83+N85+N89 -> 3.7765616 | O90: =+O83+O85+O89 -> 3.8709757 | ... AF90: =+AF83+AF85+AF89 -> 5.8901473
A92: EBITDA | C92: $mm | H92: =+H79-H90 -> 16.368787 | I92: =+I79-I90 -> 16.778006 | J92: =+J79-J90 -> 17.197456 | K92: =+K79-K90 -> 17.627393 | L92: =+L79-L90 -> 18.068078 | M92: =+M79-M90 -> 18.51978 | N92: =+N79-N90 -> 18.982774 | O92: =+O79-O90 -> 19.457343 | ... AF92: =+AF79-AF90 -> 29.606649
A94: Start-up Opex Reserve | G94: =-H90*0.5 -> -1.6282586
A96: Pre-Tax Unlevered Cash Flow | C96: $mm | E96: =-E35 -> -11.34 | F96: =-F35 -> -45.36 | G96: =G94-G35 -> -58.328259 | H96: =+H92 -> 16.368787 | I96: =+I92 -> 16.778006 | J96: =+J92 -> 17.197456 | K96: =+K92 -> 17.627393 | L96: =+L92 -> 18.068078 | M96: =+M92 -> 18.51978 | N96: =+N92 -> 18.982774 | O96: =+O92 -> 19.457343 | ... AF96: =+AF92 -> 29.606649
A98: Pre-Tax Unlevered IRR | C98: % | E98: =+IRR(E96:AF96) -> 0.14789651 | G98: Performance Liquidated Damage per 10%
A99: NPV 10 | C99: $mm | E99: =+NPV(0.1,E96:AF96) -> 44.297246 | F99: 49.219162 | G99: =E99-F99 -> -4.9219162
A101: Finance Plan
A103: Construction Debt Program
A104: Construction Debt Term | C104: Yrs | D104: =+E42 -> 3
A105: Construction Debt Rate | C105: % | D105: =+E43 -> 0.05
A106: Construction Debt Leverage | C106: % | D106: =+E44 -> 0.5
A108: S Curve-Construction Expenditure
A109: S Curve | C109: Yr | E109: Yr1 | F109: Yr2 | G109: Yr3 | I109: Total
A110: S Curve | C110: % | E110: =+E34 -> 0.1 | F110: =+F34 -> 0.4 | G110: 0.5 | I110: =+SUM(E110:G110) -> 1
A111: S Curve | C111: $mm | E111: =+E35 -> 11.34 | F111: =+F35 -> 45.36 | G111: =+G35 -> 56.7 | I111: =+SUM(E111:G111) -> 113.4
A113: Construction Finance | E113: Yr1 | F113: Yr2 | G113: Yr3
A114: Constuction Debt BOY | C114: $mm | E114: 0 | F114: =+E119 -> 5.81175 | G114: =+F119 -> 29.349338
A115: Construction Debt Add | C115: $mm | E115: =+E111*$D$106 -> 5.67 | F115: =+F111*$D$106 -> 22.68 | G115: =+G111*$D$106 -> 28.35
A116: Construction Debt EOY b4 IDC | C116: $mm | E116: =+E114+E115 -> 5.67 | F116: =+F114+F115 -> 28.49175 | G116: =+G114+G115 -> 57.699338
A117: Construction Debt Ave | C117: $mm | E117: =+(E114+E116)/2 -> 2.835 | F117: =+(F114+F116)/2 -> 17.15175 | G117: =+(G114+G116)/2 -> 43.524338
A118: Interest During Construction (IDC) | C118: $mm | E118: =+E117*$D$105 -> 0.14175 | F118: =+F117*$D$105 -> 0.8575875 | G118: =+G117*$D$105 -> 2.1762169
A119: Consturction Debt EOY a IDC | C119: $mm | E119: =+E116+E118 -> 5.81175 | F119: =+F116+F118 -> 29.349338 | G119: =+G116+G118 -> 59.875554
E121: Yr1 | F121: Yr2 | G121: Yr3
A122: Construction Equity per Year | C122: $mm | E122: =+E111-E115 -> 5.67 | F122: =+F111-F115 -> 22.68 | G122: =+G111-G115 -> 28.35
A123: Construction Equity Total | C123: $mm | E123: =+E122 -> 5.67 | F123: =+E123+F122 -> 28.35 | G123: =+F123+G122 -> 56.7
A125: Final Construction Capital Structure | E125: Yr1 | F125: Yr2 | G125: Yr3
A126: Debt @ End of Construction Loan | C126: $mm | E126: =+E119 -> 5.81175 | F126: =+F119 -> 29.349338 | G126: =+G119 -> 59.875554
A127: Equity @ End of Construction Loan | C127: $mm | E127: =+E122 -> 5.67 | F127: =+F123 -> 28.35 | G127: =+G123 -> 56.7
A128: Total Capital | C128: $mm | E128: =SUM(E126:E127) -> 11.48175 | F128: =SUM(F126:F127) -> 57.699338 | G128: =SUM(G126:G127) -> 116.57555
A130: Take-Out Finance Program
A132: Take-Out Loan Program
A133: Take-Out Debt Term | C133: Yrs | D133: =+E46 -> 15
A134: Take-Out Debt Rate | C134: % | D134: =+E47 -> 0.065
A135: Take-Out Debt Leverage | C135: % | D135: =+E48 -> 0.59555421
A137: Take-Out Capital Structure
...

Sheet Schedule LD
A1: In Class Case Study Model
A3: Technology | C3: Wind Energy Turbine
A5: Capacity | C5: =+'[1]Base Data'!D5 -> MW | E5: =VLOOKUP('Schedule LD'!A5,Table1[#All],8,FALSE) -> 80
A6: Capacity Factor: Note 2 | C6: =+'[1]Base Data'!D15 -> % | E6: =VLOOKUP('Schedule LD'!A6,Table1[#All],8,FALSE) -> 0.4
A7: Annual Production | C7: MWH | E7: =+E5*8760*E6 -> 280320
A8: Heat Rate/Fuel Rate | C8: btu/kwh | E8: =VLOOKUP('Schedule LD'!A8,Table1[#All],8,FALSE) -> 0
A9: Fixed O&M | C9: $/kw/yr | E9: =VLOOKUP('Schedule LD'!A9,Table1[#All],8,FALSE) -> 42
A10: Variable O&M | C10: $/mwh | E10: =VLOOKUP('Schedule LD'!A10,Table1[#All],8,FALSE) -> 0
A11: Capital Cost: Note 1 | C11: =+'[1]Base Data'!D6 -> $/kw | E11: =VLOOKUP('Schedule LD'!A11,Table1[#All],8,FALSE) -> 1500
A12: EPC Capital Cost* | C12: $mm | E12: =+E5*E11*1000/1000000 -> 120
A13: Construction Debt Term | C13: Yrs | E13: =VLOOKUP('Schedule LD'!A13,Table1[#All],8,FALSE) -> 3
A14: S Curve for EPC Capital Cost* | C14: Yr | E14: Y1 | F14: Yr2 | G14: Yr3
A15: S Curve for EPC Capital Cost* | C15: % | E15: 0.1 | F15: 0.4 | G15: 0.5
A16: S Curve for EPC Capital Cost* | C16: $mm | E16: =+E12*E15 -> 12 | F16: =+E12*F15 -> 48 | G16: =+E12*G15 -> 60
A17: Cost Inflation Rate | C17: % | E17: =VLOOKUP('Schedule LD'!A17,Table1[#All],8,FALSE) -> 0.025
A18: Economic Life | C18: Years | E18: =VLOOKUP('Schedule LD'!A18,Table1[#All],8,FALSE) -> 25
A19: Tax Rate | C19: Federal | E19: =VLOOKUP('Schedule LD'!A19,Table1[#All],8,FALSE) -> 0.21
A20: Tax Depreciation | C20: MACRS | E20: =VLOOKUP('Schedule LD'!A20,Table1[#All],8,FALSE) -> 5 | H20: Year 1 | I20: Year 2 | J20: Year 3 | K20: Year 4 | L20: Year 5 | M20: Year 6
A21: Tax Depreciation Rate | C21: % | H21: 0.2 | I21: 0.32 | J21: 0.192 | K21: 0.1152 | L21: 0.1152 | M21: 0.0576
A22: CO2 Emissions | C22: lbs/mmbtu | E22: 0
A23: Potential Carbon Tax | C23: $/ton | E23: 0
A25: *Excludes any development fee or interest during construction
A28: Development Fee Bonus
A30: Development Fee Bonus | C30: % EPC Capital Cost | E30: 0.05
A31: Development Fee Bonus | C31: $mm | E31: =+E30*E12 -> 6
A32: Capital Cost Including Development Fee | E32: =+E12+E31 -> 126
A33: S Curve for Total Capital Cost** | C33: Yr | E33: Yr1 | F33: Yr2 | G33: Yr3
A34: S Curve for Total Capital Cost** | C34: % | E34: 0.1 | F34: 0.4 | G34: 0.5
A35: S Curve for Total Capital Cost** | C35: $mm | E35: =+E34*$E$32 -> 12.6 | F35: =+F34*$E$32 -> 50.4 | G35: =+G34*$E$32 -> 63
A37: **Includes development fee but excludes interest during construction
A40: Construction Finance and Take Out Finance
A42: Construction Debt Term | C42: Yrs | E42: 3
A43: Construction Debt Rate | C43: % | E43: 0.05
A44: Construction Debt Leverage | C44: % | E44: 0.5
A46: Take-Out Debt Term | C46: Yrs | E46: 15
A47: Take-Out Debt Rate | C47: % | E47: 0.065
A48: Take-Out Debt Leverage | C48: % | E48: 0.59555421
A50: Take Out Debt is to be structrued with a mortgage style amortization with
A51: equal debt service amounts over the entire take-out term of 15 years
A53: In addition to the capital cost from the EPC contract and the Development Fee Bonus
A54: fund a 6 month debt service reserve and six months
A55: of estimated start up costs along with the final construction finance payments
A58: Fuel Contract with NatGas Co
A60: Base Price in 2025 | C60: $/mmbtu | E60: 0
A61: Fuel Price Escalator | C61: % | E61: 0
A63: Off-Take Agreement with Ready Kilowatt Power Co. | E63: Initial Offer | G63: Response
A65: Base Price in 2025 | C65: $/MWH | E65: 35 | G65: 72.235087
A66: Fuel Price Escalator | C66: % | E66: 0 | G66: 0
A69: Project Finanacial and Operating Plan
A71: Income Statement | E71: 2025 | F71: =+E71+1 -> 2026 | G71: =+F71+1 -> 2027 | I71: =+G71+1 -> 2028 | J71: =+I71+1 -> 2029 | K71: =+J71+1 -> 2030 | L71: =+K71+1 -> 2031 | M71: =+L71+1 -> 2032 | N71: =+M71+1 -> 2033 | O71: 2034 | P71: =+O71+1 -> 2035 | Q71: 2036 | R71: 2037 | S71: 2038 | T71: =+S71+1 -> 2039 | U71: =+T71+1 -> 2040 | V71: =+U71+1 -> 2041 | W71: 2039 | X71: =+W71+1 -> 2040 | Y71: =+X71+1 -> 2041 | Z71: =+Y71+1 -> 2042 | AA71: 2040 | AB71: =+AA71+1 -> 2041 | AC71: =+AB71+1 -> 2042 | AD71: =+AC71+1 -> 2043 | AE71: 2041 | AF71: =+AE71+1 -> 2042 | AG71: =+AF71+1 -> 2043
A73: Project Year | I73: 1 | J73: =+I73+1 -> 2 | K73: =+J73+1 -> 3 | L73: =+K73+1 -> 4 | M73: =+L73+1 -> 5 | N73: =+M73+1 -> 6 | O73: =+N73+1 -> 7 | P73: =+O73+1 -> 8 | Q73: =+P73+1 -> 9 | ... AG73: =+AF73+1 -> 25
A74: Construction Year | E74: 1 | F74: 2 | G74: 3
A76: Revenues
A77: Production | C77: MWH | I77: =+$E$7 -> 280320 | J77: =+$E$7 -> 280320 | K77: =+$E$7 -> 280320 | L77: =+$E$7 -> 280320 | M77: =+$E$7 -> 280320 | N77: =+$E$7 -> 280320 | O77: =+$E$7 -> 280320 | P77: =+$E$7 -> 280320 | ... AG77: =+$E$7 -> 280320
A78: Price | C78: $/MWH | E78: =+G65 -> 72.235087 | F78: =E78*1.025 -> 74.040964 | G78: =F78*1.025 -> 75.891988 | H78: =G78*1.025 -> 77.789288 | I78: =H78*1.025 -> 79.73402 | J78: =I78*1.025 -> 81.72737 | K78: =J78*1.025 -> 83.770555 | L78: =K78*1.025 -> 85.864818 | M78: =L78*1.025 -> 88.011439 | ... AG78: =AF78*1.025 -> 144.21699
A79: Total Revenues | C79: $mm | I79: =+I77*I78/1000000 -> 22.35104 | J79: =+J77*J78/1000000 -> 22.909816 | K79: =+K77*K78/1000000 -> 23.482562 | L79: =+L77*L78/1000000 -> 24.069626 | M79: =+M77*M78/1000000 -> 24.671367 | N79: =+N77*N78/1000000 -> 25.288151 | O79: =+O77*O78/1000000 -> 25.920354 | P79: =+P77*P78/1000000 -> 26.568363 | ... AG79: =+AG77*AG78/1000000 -> 40.426907
A81: Expense
A82: Fixed O&M | C82: $/kw | E82: =+E9 -> 42 | F82: =+E82*(1+$E$17) -> 43.05 | G82: =+F82*(1+$E$17) -> 44.12625 | H82: =G82*1.025 -> 45.229406 | I82: =+G82*(1+$E$17) -> 45.229406 | J82: =+I82*(1+$E$17) -> 46.360141 | K82: =+J82*(1+$E$17) -> 47.519145 | L82: =+K82*(1+$E$17) -> 48.707124 | M82: =+L82*(1+$E$17) -> 49.924802 | N82: =+M82*(1+$E$17) -> 51.172922 | O82: =+N82*(1+$E$17) -> 52.452245 | P82: =+O82*(1+$E$17) -> 53.763551 | Q82: =+P82*(1+$E$17) -> 55.10764 | ... AG82: =+AF82*(1+$E$17) -> 81.807601
A83: Fixed O&M | C83: $mm | I83: =+I82*$E$5*1000/1000000 -> 3.6183525 | J83: =+J82*$E$5*1000/1000000 -> 3.7088113 | K83: =+K82*$E$5*1000/1000000 -> 3.8015316 | L83: =+L82*$E$5*1000/1000000 -> 3.8965699 | M83: =+M82*$E$5*1000/1000000 -> 3.9939841 | N83: =+N82*$E$5*1000/1000000 -> 4.0938337 | O83: =+O82*$E$5*1000/1000000 -> 4.1961796 | P83: =+P82*$E$5*1000/1000000 -> 4.3010841 | ... AG83: =+AG82*$E$5*1000/1000000 -> 6.5446081
A84: Variable O&M | C84: $/MWH | E84: =+E10 -> 0 | F84: =+E84*(1+$E$17) -> 0 | G84: =+F84*(1+$E$17) -> 0 | I84: =+G84*(1+$E$17) -> 0 | J84: =+I84*(1+$E$17) -> 0 | K84: =+J84*(1+$E$17) -> 0 | L84: =+K84*(1+$E$17) -> 0 | M84: =+L84*(1+$E$17) -> 0 | N84: =+M84*(1+$E$17) -> 0
A85: Variable O&M | C85: $mm | I85: =+I77*I84/1000000 -> 0 | J85: =+J77*J84/1000000 -> 0 | K85: =+K77*K84/1000000 -> 0 | L85: =+L77*L84/1000000 -> 0 | M85: =+M77*M84/1000000 -> 0 | N85: =+N77*N84/1000000 -> 0
A86: Heat Rate | C86: btu/kwh | I86: =+$E$8 -> 0 | J86: =+$E$8 -> 0 | K86: =+$E$8 -> 0 | L86: =+$E$8 -> 0 | M86: =+$E$8 -> 0 | N86: =+$E$8 -> 0
A87: Fuel Requirment | C87: mmbtus | I87: =+I86*I77*1000/1000000 -> 0 | J87: =+J86*J77*1000/1000000 -> 0 | K87: =+K86*K77*1000/1000000 -> 0 | L87: =+L86*L77*1000/1000000 -> 0 | M87: =+M86*M77*1000/1000000 -> 0 | N87: =+N86*N77*1000/1000000 -> 0
A88: Fuel price | C88: $/mmbtu | E88: =+E60 -> 0 | F88: =+E88*(1+$E$61) -> 0 | G88: =+F88*(1+$E$61) -> 0 | I88: =+G88*(1+$E$61) -> 0 | J88: =+I88*(1+$E$61) -> 0 | K88: =+J88*(1+$E$61) -> 0 | L88: =+K88*(1+$E$61) -> 0 | M88: =+L88*(1+$E$61) -> 0 | N88: =+M88*(1+$E$61) -> 0
A89: Fuel Cost | C89: $mm | I89: =+I87*I88/1000000 -> 0 | J89: =+J87*J88/1000000 -> 0 | K89: =+K87*K88/1000000 -> 0 | L89: =+L87*L88/1000000 -> 0 | M89: =+M87*M88/1000000 -> 0 | N89: =+N87*N88/1000000 -> 0
A90: Total Expense | C90: $mm | I90: =+I83+I85+I89 -> 3.6183525 | J90: =+J83+J85+J89 -> 3.7088113 | K90: =+K83+K85+K89 -> 3.8015316 | L90: =+L83+L85+L89 -> 3.8965699 | M90: =+M83+M85+M89 -> 3.9939841 | N90: =+N83+N85+N89 -> 4.0938337 | O90: =+O83+O85+O89 -> 4.1961796 | P90: =+P83+P85+P89 -> 4.3010841 | ... AG90: =+AG83+AG85+AG89 -> 6.5446081
A92: EBITDA | C92: $mm | I92: =+I79-I90 -> 18.732688 | J92: =+J79-J90 -> 19.201005 | K92: =+K79-K90 -> 19.68103 | L92: =+L79-L90 -> 20.173056 | M92: =+M79-M90 -> 20.677382 | N92: =+N79-N90 -> 21.194317 | O92: =+O79-O90 -> 21.724175 | P92: =+P79-P90 -> 22.267279 | ... AG92: =+AG79-AG90 -> 33.882299
A94: Start-up Opex Reserve | G94: =-I90*0.5 -> -1.8091762
A96: Pre-Tax Unlevered Cash Flow | C96: $mm | E96: =-E35 -> -12.6 | F96: =-F35 -> -50.4 | G96: =G94-G35 -> -64.809176 | H96: 0 | I96: =+I92 -> 18.732688 | J96: =+J92 -> 19.201005 | K96: =+K92 -> 19.68103 | L96: =+L92 -> 20.173056 | M96: =+M92 -> 20.677382 | N96: =+N92 -> 21.194317 | O96: =+O92 -> 21.724175 | P96: =+P92 -> 22.267279 | ... AG96: =+AG92 -> 33.882299
A98: Pre-Tax Unlevered IRR | C98: % | E98: =+IRR(E96:AG96) -> 0.13505309 | G98: Loss per calendar year of delay(365 days)
A99: NPV 10 | C99: $mm | E99: =+NPV(0.1,E96:AG96) -> 39.605266 | F99: 49.219162 | G99: =E99-F99 -> -9.6138954 | H99: =G99/365 -> -0.026339439 | I99: =H99*1000000 -> -26339.439
A101: Finance Plan
A103: Construction Debt Program
A104: Construction Debt Term | C104: Yrs | D104: =+E42 -> 3
A105: Construction Debt Rate | C105: % | D105: =+E43 -> 0.05
A106: Construction Debt Leverage | C106: % | D106: =+E44 -> 0.5
A108: S Curve-Construction Expenditure
A109: S Curve | C109: Yr | E109: Yr1 | F109: Yr2 | G109: Yr3 | I109: Total
A110: S Curve | C110: % | E110: =+E34 -> 0.1 | F110: =+F34 -> 0.4 | G110: 0.5 | I110: =+SUM(E110:G110) -> 1
A111: S Curve | C111: $mm | E111: =+E35 -> 12.6 | F111: =+F35 -> 50.4 | G111: =+G35 -> 63 | I111: =+SUM(E111:G111) -> 126
A113: Construction Finance | E113: Yr1 | F113: Yr2 | G113: Yr3
A114: Constuction Debt BOY | C114: $mm | E114: 0 | F114: =+E119 -> 6.4575 | G114: =+F119 -> 32.610375
A115: Construction Debt Add | C115: $mm | E115: =+E111*$D$106 -> 6.3 | F115: =+F111*$D$106 -> 25.2 | G115: =+G111*$D$106 -> 31.5
A116: Construction Debt EOY b4 IDC | C116: $mm | E116: =+E114+E115 -> 6.3 | F116: =+F114+F115 -> 31.6575 | G116: =+G114+G115 -> 64.110375
A117: Construction Debt Ave | C117: $mm | E117: =+(E114+E116)/2 -> 3.15 | F117: =+(F114+F116)/2 -> 19.0575 | G117: =+(G114+G116)/2 -> 48.360375
A118: Interest During Construction (IDC) | C118: $mm | E118: =+E117*$D$105 -> 0.1575 | F118: =+F117*$D$105 -> 0.952875 | G118: =+G117*$D$105 -> 2.4180188
A119: Consturction Debt EOY a IDC | C119: $mm | E119: =+E116+E118 -> 6.4575 | F119: =+F116+F118 -> 32.610375 | G119: =+G116+G118 -> 66.528394
E121: Yr1 | F121: Yr2 | G121: Yr3
A122: Construction Equity per Year | C122: $mm | E122: =+E111-E115 -> 6.3 | F122: =+F111-F115 -> 25.2 | G122: =+G111-G115 -> 31.5
A123: Construction Equity Total | C123: $mm | E123: =+E122 -> 6.3 | F123: =+E123+F122 -> 31.5 | G123: =+F123+G122 -> 63
A125: Final Construction Capital Structure | E125: Yr1 | F125: Yr2 | G125: Yr3
A126: Debt @ End of Construction Loan | C126: $mm | E126: =+E119 -> 6.4575 | F126: =+F119 -> 32.610375 | G126: =+G119 -> 66.528394
A127: Equity @ End of Construction Loan | C127: $mm | E127: =+E122 -> 6.3 | F127: =+F123 -> 31.5 | G127: =+G123 -> 63
A128: Total Capital | C128: $mm | E128: =SUM(E126:E127) -> 12.7575 | F128: =SUM(F126:F127) -> 64.110375 | G128: =SUM(G126:G127) -> 129.52839
A130: Take-Out Finance Program
A132: Take-Out Loan Program
A133: Take-Out Debt Term | C133: Yrs | D133: =+E46 -> 15
A134: Take-Out Debt Rate | C134: % | D134: =+E47 -> 0.065
A135: Take-Out Debt Leverage | C135: % | D135: =+E48 -> 0.59555421
A137: Take-Out Capital Structure
...

Sheet Residual
A1: In Class Case Study Model
A3: Technology | C3: Wind Energy Turbine
A5: Capacity | C5: =+'[1]Base Data'!D5 -> MW | E5: =VLOOKUP(Residual!A5,Table1[#All],8,FALSE) -> 80
A6: Capacity Factor: Note 2 | C6: =+'[1]Base Data'!D15 -> % | E6: =VLOOKUP(Residual!A6,Table1[#All],8,FALSE) -> 0.4
A7: Annual Production | C7: MWH | E7: =+E5*8760*E6 -> 280320
A8: Heat Rate/Fuel Rate | C8: btu/kwh | E8: =VLOOKUP(Residual!A8,Table1[#All],8,FALSE) -> 0
A9: Fixed O&M | C9: $/kw/yr | E9: =VLOOKUP(Residual!A9,Table1[#All],8,FALSE) -> 42
A10: Variable O&M | C10: $/mwh | E10: =VLOOKUP(Residual!A10,Table1[#All],8,FALSE) -> 0
A11: Capital Cost: Note 1 | C11: =+'[1]Base Data'!D6 -> $/kw | E11: =VLOOKUP(Residual!A11,Table1[#All],8,FALSE) -> 1500
A12: EPC Capital Cost* | C12: $mm | E12: =+E5*E11*1000/1000000 -> 120
A13: Construction Debt Term | C13: Yrs | E13: =VLOOKUP(Residual!A13,Table1[#All],8,FALSE) -> 3
A14: S Curve for EPC Capital Cost* | C14: Yr | E14: Y1 | F14: Yr2 | G14: Yr3
A15: S Curve for EPC Capital Cost* | C15: % | E15: 0.1 | F15: 0.4 | G15: 0.5
A16: S Curve for EPC Capital Cost* | C16: $mm | E16: =+E12*E15 -> 12 | F16: =+E12*F15 -> 48 | G16: =+E12*G15 -> 60
A17: Cost Inflation Rate | C17: % | E17: =VLOOKUP(Residual!A17,Table1[#All],8,FALSE) -> 0.025
A18: Economic Life | C18: Years | E18: =VLOOKUP(Residual!A18,Table1[#All],8,FALSE) -> 25
A19: Tax Rate | C19: Federal | E19: =VLOOKUP(Residual!A19,Table1[#All],8,FALSE) -> 0.21
A20: Tax Depreciation | C20: MACRS | E20: =VLOOKUP(Residual!A20,Table1[#All],8,FALSE) -> 5 | H20: Year 1 | I20: Year 2 | J20: Year 3 | K20: Year 4 | L20: Year 5 | M20: Year 6
A21: Tax Depreciation Rate | C21: % | H21: 0.2 | I21: 0.32 | J21: 0.192 | K21: 0.1152 | L21: 0.1152 | M21: 0.0576
A22: CO2 Emissions | C22: lbs/mmbtu | E22: 0
A23: Potential Carbon Tax | C23: $/ton | E23: 0
A25: *Excludes any development fee or interest during construction
A28: Development Fee Bonus
A30: Development Fee Bonus | C30: % EPC Capital Cost | E30: 0.05
A31: Development Fee Bonus | C31: $mm | E31: =+E30*E12 -> 6
A32: Capital Cost Including Development Fee | E32: =+E12+E31 -> 126
A33: S Curve for Total Capital Cost** | C33: Yr | E33: Yr1 | F33: Yr2 | G33: Yr3
A34: S Curve for Total Capital Cost** | C34: % | E34: 0.1 | F34: 0.4 | G34: 0.5
A35: S Curve for Total Capital Cost** | C35: $mm | E35: =+E34*$E$32 -> 12.6 | F35: =+F34*$E$32 -> 50.4 | G35: =+G34*$E$32 -> 63
A37: **Includes development fee but excludes interest during construction
A40: Construction Finance and Take Out Finance
A42: Construction Debt Term | C42: Yrs | E42: 3
A43: Construction Debt Rate | C43: % | E43: 0.05
A44: Construction Debt Leverage | C44: % | E44: 0.5
A46: Take-Out Debt Term | C46: Yrs | E46: 15
A47: Take-Out Debt Rate | C47: % | E47: 0.065
A48: Take-Out Debt Leverage | C48: % | E48: 0.59555421
A50: Take Out Debt is to be structrued with a mortgage style amortization with
A51: equal debt service amounts over the entire take-out term of 15 years
A53: In addition to the capital cost from the EPC contract and the Development Fee Bonus
A54: fund a 6 month debt service reserve and six months
A55: of estimated start up costs along with the final construction finance payments
A58: Fuel Contract with NatGas Co
A60: Base Price in 2025 | C60: $/mmbtu | E60: 0
A61: Fuel Price Escalator | C61: % | E61: 0
A63: Off-Take Agreement with Ready Kilowatt Power Co. | E63: Initial Offer | G63: Response
A65: Base Price in 2025 | C65: $/MWH | E65: 35 | G65: 72.235087
A66: Fuel Price Escalator | C66: % | E66: 0 | G66: 0
A69: Project Finanacial and Operating Plan
A71: Income Statement | E71: 2025 | F71: =+E71+1 -> 2026 | G71: =+F71+1 -> 2027 | H71: =+G71+1 -> 2028 | I71: =+H71+1 -> 2029 | J71: =+I71+1 -> 2030 | K71: =+J71+1 -> 2031 | L71: =+K71+1 -> 2032 | M71: =+L71+1 -> 2033 | N71: 2034 | O71: =+N71+1 -> 2035 | P71: 2036 | Q71: 2037
A73: Project Year | H73: 1 | I73: =+H73+1 -> 2 | J73: =+I73+1 -> 3 | K73: =+J73+1 -> 4 | L73: =+K73+1 -> 5 | M73: =+L73+1 -> 6 | N73: =+M73+1 -> 7 | O73: =+N73+1 -> 8 | P73: =+O73+1 -> 9 | Q73: =+P73+1 -> 10
A74: Construction Year | E74: 1 | F74: 2 | G74: 3
A76: Revenues
A77: Production | C77: MWH | H77: =+$E$7 -> 280320 | I77: =+$E$7 -> 280320 | J77: =+$E$7 -> 280320 | K77: =+$E$7 -> 280320 | L77: =+$E$7 -> 280320 | M77: =+$E$7 -> 280320 | N77: =+$E$7 -> 280320 | O77: =+$E$7 -> 280320 | ... Q77: =+$E$7 -> 280320
A78: Price | C78: $/MWH | E78: =+G65 -> 72.235087 | F78: =E78*1.025 -> 74.040964 | G78: =F78*1.025 -> 75.891988 | H78: =G78*1.025 -> 77.789288 | I78: =H78*1.025 -> 79.73402 | J78: =I78*1.025 -> 81.72737 | K78: =J78*1.025 -> 83.770555 | L78: =K78*1.025 -> 85.864818 | M78: =L78*1.025 -> 88.011439 | ... Q78: =P78*1.025 -> 97.148161
A79: Total Revenues | C79: $mm | H79: =+H77*H78/1000000 -> 21.805893 | I79: =+I77*I78/1000000 -> 22.35104 | J79: =+J77*J78/1000000 -> 22.909816 | K79: =+K77*K78/1000000 -> 23.482562 | L79: =+L77*L78/1000000 -> 24.069626 | M79: =+M77*M78/1000000 -> 24.671367 | N79: =+N77*N78/1000000 -> 25.288151 | O79: =+O77*O78/1000000 -> 25.920354 | ... Q79: =+Q77*Q78/1000000 -> 27.232572
A81: Expense
A82: Fixed O&M | C82: $/kw | E82: =+E9 -> 42 | F82: =+E82*(1+$E$17) -> 43.05 | G82: =+F82*(1+$E$17) -> 44.12625 | H82: =+G82*(1+$E$17) -> 45.229406 | I82: =+H82*(1+$E$17) -> 46.360141 | J82: =+I82*(1+$E$17) -> 47.519145 | K82: =+J82*(1+$E$17) -> 48.707124 | L82: =+K82*(1+$E$17) -> 49.924802 | M82: =+L82*(1+$E$17) -> 51.172922 | ... Q82: =+P82*(1+$E$17) -> 56.485331
A83: Fixed O&M | C83: $mm | H83: =+H82*$E$5*1000/1000000 -> 3.6183525 | I83: =+I82*$E$5*1000/1000000 -> 3.7088113 | J83: =+J82*$E$5*1000/1000000 -> 3.8015316 | K83: =+K82*$E$5*1000/1000000 -> 3.8965699 | L83: =+L82*$E$5*1000/1000000 -> 3.9939841 | M83: =+M82*$E$5*1000/1000000 -> 4.0938337 | N83: =+N82*$E$5*1000/1000000 -> 4.1961796 | O83: =+O82*$E$5*1000/1000000 -> 4.3010841 | ... Q83: =+Q82*$E$5*1000/1000000 -> 4.5188264
A84: Variable O&M | C84: $/MWH | E84: =+E10 -> 0 | F84: =+E84*(1+$E$17) -> 0 | G84: =+F84*(1+$E$17) -> 0 | H84: =+G84*(1+$E$17) -> 0 | I84: =+H84*(1+$E$17) -> 0 | J84: =+I84*(1+$E$17) -> 0 | K84: =+J84*(1+$E$17) -> 0 | L84: =+K84*(1+$E$17) -> 0 | M84: =+L84*(1+$E$17) -> 0
A85: Variable O&M | C85: $mm | H85: =+H77*H84/1000000 -> 0 | I85: =+I77*I84/1000000 -> 0 | J85: =+J77*J84/1000000 -> 0 | K85: =+K77*K84/1000000 -> 0 | L85: =+L77*L84/1000000 -> 0 | M85: =+M77*M84/1000000 -> 0
A86: Heat Rate | C86: btu/kwh | H86: =+$E$8 -> 0 | I86: =+$E$8 -> 0 | J86: =+$E$8 -> 0 | K86: =+$E$8 -> 0 | L86: =+$E$8 -> 0 | M86: =+$E$8 -> 0
A87: Fuel Requirment | C87: mmbtus | H87: =+H86*H77*1000/1000000 -> 0 | I87: =+I86*I77*1000/1000000 -> 0 | J87: =+J86*J77*1000/1000000 -> 0 | K87: =+K86*K77*1000/1000000 -> 0 | L87: =+L86*L77*1000/1000000 -> 0 | M87: =+M86*M77*1000/1000000 -> 0
A88: Fuel price | C88: $/mmbtu | E88: =+E60 -> 0 | F88: =+E88*(1+$E$61) -> 0 | G88: =+F88*(1+$E$61) -> 0 | H88: =+G88*(1+$E$61) -> 0 | I88: =+H88*(1+$E$61) -> 0 | J88: =+I88*(1+$E$61) -> 0 | K88: =+J88*(1+$E$61) -> 0 | L88: =+K88*(1+$E$61) -> 0 | M88: =+L88*(1+$E$61) -> 0
A89: Fuel Cost | C89: $mm | H89: =+H87*H88/1000000 -> 0 | I89: =+I87*I88/1000000 -> 0 | J89: =+J87*J88/1000000 -> 0 | K89: =+K87*K88/1000000 -> 0 | L89: =+L87*L88/1000000 -> 0 | M89: =+M87*M88/1000000 -> 0
A90: Total Expense | C90: $mm | H90: =+H83+H85+H89 -> 3.6183525 | I90: =+I83+I85+I89 -> 3.7088113 | J90: =+J83+J85+J89 -> 3.8015316 | K90: =+K83+K85+K89 -> 3.8965699 | L90: =+L83+L85+L89 -> 3.9939841 | M90: =+M83+M85+M89 -> 4.0938337 | N90: =+N83+N85+N89 -> 4.1961796 | O90: =+O83+O85+O89 -> 4.3010841 | ... Q90: =+Q83+Q85+Q89 -> 4.5188264
A92: EBITDA | C92: $mm | H92: =+H79-H90 -> 18.187541 | I92: =+I79-I90 -> 18.642229 | J92: =+J79-J90 -> 19.108285 | K92: =+K79-K90 -> 19.585992 | L92: =+L79-L90 -> 20.075642 | M92: =+M79-M90 -> 20.577533 | N92: =+N79-N90 -> 21.091971 | O92: =+O79-O90 -> 21.61927 | ... Q92: =+Q79-Q90 -> 22.713746
A94: Start-up Opex Reserve | G94: =-H90*0.5 -> -1.8091762
A96: Pre-Tax Unlevered Cash Flow | C96: $mm | E96: =-E35 -> -12.6 | F96: =-F35 -> -50.4 | G96: =G94-G35 -> -64.809176 | H96: =+H92 -> 18.187541 | I96: =+I92 -> 18.642229 | J96: =+J92 -> 19.108285 | K96: =+K92 -> 19.585992 | L96: =+L92 -> 20.075642 | M96: =+M92 -> 20.577533 | N96: =+N92 -> 21.091971 | O96: =+O92 -> 21.61927 | ... Q96: =+Q92 -> 22.713746
A97: Residual 10 | C97: 7.5 | Q97: =+Q96*C97 -> 170.35309
E98: =+E96 -> -12.6 | F98: -50.4 | G98: -64.809176 | H98: 18.187541 | I98: 18.642229 | J98: 19.108285 | K98: 19.585992 | L98: 20.075642 | M98: 20.577533 | N98: 21.091971 | O98: 21.61927 | P98: 22.159752 | Q98: =Q97+Q96 -> 193.06684
A99: Pre-Tax Unlevered IRR | C99: % | E99: =+IRR(E98:AF98) -> 0.15256512 | G99: =SUM(E96:P96) -> 53.239039
A100: NPV 10 | C100: $mm | E100: =+NPV(0.1,E98:AF98) -> 39.821975 | G100: 49.2
A102: Finance Plan
A104: Construction Debt Program
A105: Construction Debt Term | C105: Yrs | D105: =+E42 -> 3
A106: Construction Debt Rate | C106: % | D106: =+E43 -> 0.05
A107: Construction Debt Leverage | C107: % | D107: =+E44 -> 0.5
A109: S Curve-Construction Expenditure
A110: S Curve | C110: Yr | E110: Yr1 | F110: Yr2 | G110: Yr3 | I110: Total
A111: S Curve | C111: % | E111: =+E34 -> 0.1 | F111: =+F34 -> 0.4 | G111: 0.5 | I111: =+SUM(E111:G111) -> 1
A112: S Curve | C112: $mm | E112: =+E35 -> 12.6 | F112: =+F35 -> 50.4 | G112: =+G35 -> 63 | I112: =+SUM(E112:G112) -> 126
A114: Construction Finance | E114: Yr1 | F114: Yr2 | G114: Yr3
A115: Constuction Debt BOY | C115: $mm | E115: 0 | F115: =+E120 -> 6.4575 | G115: =+F120 -> 32.610375
A116: Construction Debt Add | C116: $mm | E116: =+E112*$D$107 -> 6.3 | F116: =+F112*$D$107 -> 25.2 | G116: =+G112*$D$107 -> 31.5
A117: Construction Debt EOY b4 IDC | C117: $mm | E117: =+E115+E116 -> 6.3 | F117: =+F115+F116 -> 31.6575 | G117: =+G115+G116 -> 64.110375
A118: Construction Debt Ave | C118: $mm | E118: =+(E115+E117)/2 -> 3.15 | F118: =+(F115+F117)/2 -> 19.0575 | G118: =+(G115+G117)/2 -> 48.360375
A119: Interest During Construction (IDC) | C119: $mm | E119: =+E118*$D$106 -> 0.1575 | F119: =+F118*$D$106 -> 0.952875 | G119: =+G118*$D$106 -> 2.4180188
A120: Consturction Debt EOY a IDC | C120: $mm | E120: =+E117+E119 -> 6.4575 | F120: =+F117+F119 -> 32.610375 | G120: =+G117+G119 -> 66.528394
E122: Yr1 | F122: Yr2 | G122: Yr3
A123: Construction Equity per Year | C123: $mm | E123: =+E112-E116 -> 6.3 | F123: =+F112-F116 -> 25.2 | G123: =+G112-G116 -> 31.5
A124: Construction Equity Total | C124: $mm | E124: =+E123 -> 6.3 | F124: =+E124+F123 -> 31.5 | G124: =+F124+G123 -> 63
A126: Final Construction Capital Structure | E126: Yr1 | F126: Yr2 | G126: Yr3
A127: Debt @ End of Construction Loan | C127: $mm | E127: =+E120 -> 6.4575 | F127: =+F120 -> 32.610375 | G127: =+G120 -> 66.528394
A128: Equity @ End of Construction Loan | C128: $mm | E128: =+E123 -> 6.3 | F128: =+F124 -> 31.5 | G128: =+G124 -> 63
A129: Total Capital | C129: $mm | E129: =SUM(E127:E128) -> 12.7575 | F129: =SUM(F127:F128) -> 64.110375 | G129: =SUM(G127:G128) -> 129.52839
A131: Take-Out Finance Program
A133: Take-Out Loan Program
A134: Take-Out Debt Term | C134: Yrs | D134: =+E46 -> 15
A135: Take-Out Debt Rate | C135: % | D135: =+E47 -> 0.065
...

Sheet CCGT Model 
A1: In Class Case Study Model
A3: Technology | C3: Wind Energy Turbine
A5: Capacity | C5: =+'[1]Base Data'!D5 -> MW | E5: =VLOOKUP('CCGT Model '!A5,Table1[#All],8,FALSE) -> 80
A6: Capacity Factor: Note 2 | C6: =+'[1]Base Data'!D15 -> % | E6: =VLOOKUP('CCGT Model '!A6,Table1[#All],8,FALSE) -> 0.4
A7: Annual Production | C7: MWH | E7: =+E5*8760*E6 -> 280320
A8: Heat Rate/Fuel Rate | C8: btu/kwh | E8: =VLOOKUP('CCGT Model '!A8,Table1[#All],8,FALSE) -> 0
A9: Fixed O&M | C9: $/kw/yr | E9: =VLOOKUP('CCGT Model '!A9,Table1[#All],8,FALSE) -> 42
A10: Variable O&M | C10: $/mwh | E10: =VLOOKUP('CCGT Model '!A10,Table1[#All],8,FALSE) -> 0
A11: Capital Cost: Note 1 | C11: =+'[1]Base Data'!D6 -> $/kw | E11: =VLOOKUP('CCGT Model '!A11,Table1[#All],8,FALSE) -> 1500
A12: EPC Capital Cost* | C12: $mm | E12: =+E5*E11*1000/1000000 -> 120
A13: Construction Debt Term | C13: Yrs | E13: =VLOOKUP('CCGT Model '!A13,Table1[#All],8,FALSE) -> 3
A14: S Curve for EPC Capital Cost* | C14: Yr | E14: Y1 | F14: Yr2 | G14: Yr3
A15: S Curve for EPC Capital Cost* | C15: % | E15: 0.1 | F15: 0.4 | G15: 0.5
A16: S Curve for EPC Capital Cost* | C16: $mm | E16: =+E12*E15 -> 12 | F16: =+E12*F15 -> 48 | G16: =+E12*G15 -> 60
A17: Cost Inflation Rate | C17: % | E17: =VLOOKUP('CCGT Model '!A17,Table1[#All],8,FALSE) -> 0.025
A18: Economic Life | C18: Years | E18: =VLOOKUP('CCGT Model '!A18,Table1[#All],8,FALSE) -> 25
A19: Tax Rate | C19: Federal | E19: =VLOOKUP('CCGT Model '!A19,Table1[#All],8,FALSE) -> 0.21
A20: Tax Depreciation | C20: MACRS | E20: =VLOOKUP('CCGT Model '!A20,Table1[#All],8,FALSE) -> 5 | H20: Year 1 | I20: Year 2 | J20: Year 3 | K20: Year 4 | L20: Year 5 | M20: Year 6
A21: Tax Depreciation Rate | C21: % | H21: 0.2 | I21: 0.32 | J21: 0.192 | K21: 0.1152 | L21: 0.1152 | M21: 0.0576
A22: CO2 Emissions | C22: lbs/mmbtu | E22: 0
A23: Potential Carbon Tax | C23: $/ton | E23: 0
A25: *Excludes any development fee or interest during construction
A28: Development Fee Bonus
A30: Development Fee Bonus | C30: % EPC Capital Cost | E30: 0.05
A31: Development Fee Bonus | C31: $mm | E31: =+E30*E12 -> 6
A32: Capital Cost Including Development Fee | E32: =+E12+E31 -> 126
A33: S Curve for Total Capital Cost** | C33: Yr | E33: Yr1 | F33: Yr2 | G33: Yr3
A34: S Curve for Total Capital Cost** | C34: % | E34: 0.1 | F34: 0.4 | G34: 0.5
A35: S Curve for Total Capital Cost** | C35: $mm | E35: =+E34*$E$32 -> 12.6 | F35: =+F34*$E$32 -> 50.4 | G35: =+G34*$E$32 -> 63
A37: **Includes development fee but excludes interest during construction
A40: Construction Finance and Take Out Finance
A42: Construction Debt Term | C42: Yrs | E42: 3
A43: Construction Debt Rate | C43: % | E43: 0.05
A44: Construction Debt Leverage | C44: % | E44: 0.5
A46: Take-Out Debt Term | C46: Yrs | E46: 15
A47: Take-Out Debt Rate | C47: % | E47: 0.065
A48: Take-Out Debt Leverage | C48: % | E48: 0.59555421
A50: Take Out Debt is to be structrued with a mortgage style amortization with
A51: equal debt service amounts over the entire take-out term of 15 years
A53: In addition to the capital cost from the EPC contract and the Development Fee Bonus
A54: fund a 6 month debt service reserve and six months
A55: of estimated start up costs along with the final construction finance payments
A58: Fuel Contract with NatGas Co
A60: Base Price in 2025 | C60: $/mmbtu | E60: 0
A61: Fuel Price Escalator | C61: % | E61: 0
A63: Off-Take Agreement with Ready Kilowatt Power Co. | E63: Initial Offer | G63: Response
A65: Base Price in 2025 | C65: $/MWH | E65: 35 | G65: 72.235087
A66: Fuel Price Escalator | C66: % | E66: 0 | G66: 0
A69: Project Finanacial and Operating Plan
A71: Income Statement | E71: 2025 | F71: =+E71+1 -> 2026 | G71: =+F71+1 -> 2027 | H71: =+G71+1 -> 2028 | I71: =+H71+1 -> 2029 | J71: =+I71+1 -> 2030 | K71: =+J71+1 -> 2031 | L71: =+K71+1 -> 2032 | M71: =+L71+1 -> 2033 | N71: 2034 | O71: =+N71+1 -> 2035 | P71: 2036 | Q71: 2037 | R71: 2038 | S71: =+R71+1 -> 2039 | T71: =+S71+1 -> 2040 | U71: =+T71+1 -> 2041 | V71: 2039 | W71: =+V71+1 -> 2040 | X71: =+W71+1 -> 2041 | Y71: =+X71+1 -> 2042 | Z71: 2040 | AA71: =+Z71+1 -> 2041 | AB71: =+AA71+1 -> 2042 | AC71: =+AB71+1 -> 2043 | AD71: 2041 | AE71: =+AD71+1 -> 2042 | AF71: =+AE71+1 -> 2043
A73: Project Year | H73: 1 | I73: =+H73+1 -> 2 | J73: =+I73+1 -> 3 | K73: =+J73+1 -> 4 | L73: =+K73+1 -> 5 | M73: =+L73+1 -> 6 | N73: =+M73+1 -> 7 | O73: =+N73+1 -> 8 | P73: =+O73+1 -> 9 | ... AF73: =+AE73+1 -> 25
A74: Construction Year | E74: 1 | F74: 2 | G74: 3
A76: Revenues
A77: Production | C77: MWH | H77: =+$E$7 -> 280320 | I77: =+$E$7 -> 280320 | J77: =+$E$7 -> 280320 | K77: =+$E$7 -> 280320 | L77: =+$E$7 -> 280320 | M77: =+$E$7 -> 280320 | N77: =+$E$7 -> 280320 | O77: =+$E$7 -> 280320 | ... AF77: =+$E$7 -> 280320
A78: Price | C78: $/MWH | E78: =+G65 -> 72.235087 | F78: =E78*1.025 -> 74.040964 | G78: =F78*1.025 -> 75.891988 | H78: =G78*1.025 -> 77.789288 | I78: =H78*1.025 -> 79.73402 | J78: =I78*1.025 -> 81.72737 | K78: =J78*1.025 -> 83.770555 | L78: =K78*1.025 -> 85.864818 | M78: =L78*1.025 -> 88.011439 | ... AF78: =AE78*1.025 -> 140.6995
A79: Total Revenues | C79: $mm | H79: =+H77*H78/1000000 -> 21.805893 | I79: =+I77*I78/1000000 -> 22.35104 | J79: =+J77*J78/1000000 -> 22.909816 | K79: =+K77*K78/1000000 -> 23.482562 | L79: =+L77*L78/1000000 -> 24.069626 | M79: =+M77*M78/1000000 -> 24.671367 | N79: =+N77*N78/1000000 -> 25.288151 | O79: =+O77*O78/1000000 -> 25.920354 | ... AF79: =+AF77*AF78/1000000 -> 39.440885
A81: Expense
A82: Fixed O&M | C82: $/kw | E82: =+E9 -> 42 | F82: =+E82*(1+$E$17) -> 43.05 | G82: =+F82*(1+$E$17) -> 44.12625 | H82: =+G82*(1+$E$17) -> 45.229406 | I82: =+H82*(1+$E$17) -> 46.360141 | J82: =+I82*(1+$E$17) -> 47.519145 | K82: =+J82*(1+$E$17) -> 48.707124 | L82: =+K82*(1+$E$17) -> 49.924802 | M82: =+L82*(1+$E$17) -> 51.172922 | ... AF82: =+AE82*(1+$E$17) -> 81.807601
A83: Fixed O&M | C83: $mm | H83: =+H82*$E$5*1000/1000000 -> 3.6183525 | I83: =+I82*$E$5*1000/1000000 -> 3.7088113 | J83: =+J82*$E$5*1000/1000000 -> 3.8015316 | K83: =+K82*$E$5*1000/1000000 -> 3.8965699 | L83: =+L82*$E$5*1000/1000000 -> 3.9939841 | M83: =+M82*$E$5*1000/1000000 -> 4.0938337 | N83: =+N82*$E$5*1000/1000000 -> 4.1961796 | O83: =+O82*$E$5*1000/1000000 -> 4.3010841 | ... AF83: =+AF82*$E$5*1000/1000000 -> 6.5446081
A84: Variable O&M | C84: $/MWH | E84: =+E10 -> 0 | F84: =+E84*(1+$E$17) -> 0 | G84: =+F84*(1+$E$17) -> 0 | H84: =+G84*(1+$E$17) -> 0 | I84: =+H84*(1+$E$17) -> 0 | J84: =+I84*(1+$E$17) -> 0 | K84: =+J84*(1+$E$17) -> 0 | L84: =+K84*(1+$E$17) -> 0 | M84: =+L84*(1+$E$17) -> 0
A85: Variable O&M | C85: $mm | H85: =+H77*H84/1000000 -> 0 | I85: =+I77*I84/1000000 -> 0 | J85: =+J77*J84/1000000 -> 0 | K85: =+K77*K84/1000000 -> 0 | L85: =+L77*L84/1000000 -> 0 | M85: =+M77*M84/1000000 -> 0
A86: Heat Rate | C86: btu/kwh | H86: =+$E$8 -> 0 | I86: =+$E$8 -> 0 | J86: =+$E$8 -> 0 | K86: =+$E$8 -> 0 | L86: =+$E$8 -> 0 | M86: =+$E$8 -> 0
A87: Fuel Requirment | C87: mmbtus | H87: =+H86*H77*1000/1000000 -> 0 | I87: =+I86*I77*1000/1000000 -> 0 | J87: =+J86*J77*1000/1000000 -> 0 | K87: =+K86*K77*1000/1000000 -> 0 | L87: =+L86*L77*1000/1000000 -> 0 | M87: =+M86*M77*1000/1000000 -> 0
A88: Fuel price | C88: $/mmbtu | E88: =+E60 -> 0 | F88: =+E88*(1+$E$61) -> 0 | G88: =+F88*(1+$E$61) -> 0 | H88: =+G88*(1+$E$61) -> 0 | I88: =+H88*(1+$E$61) -> 0 | J88: =+I88*(1+$E$61) -> 0 | K88: =+J88*(1+$E$61) -> 0 | L88: =+K88*(1+$E$61) -> 0 | M88: =+L88*(1+$E$61) -> 0
A89: Fuel Cost | C89: $mm | H89: =+H87*H88/1000000 -> 0 | I89: =+I87*I88/1000000 -> 0 | J89: =+J87*J88/1000000 -> 0 | K89: =+K87*K88/1000000 -> 0 | L89: =+L87*L88/1000000 -> 0 | M89: =+M87*M88/1000000 -> 0
A90: Total Expense | C90: $mm | H90: =+H83+H85+H89 -> 3.6183525 | I90: =+I83+I85+I89 -> 3.7088113 | J90: =+J83+J85+J89 -> 3.8015316 | K90: =+K83+K85+K89 -> 3.8965699 | L90: =+L83+L85+L89 -> 3.9939841 | M90: =+M83+M85+M89 -> 4.0938337 | N90: =+N83+N85+N89 -> 4.1961796 | O90: =+O83+O85+O89 -> 4.3010841 | ... AF90: =+AF83+AF85+AF89 -> 6.5446081
A92: EBITDA | C92: $mm | H92: =+H79-H90 -> 18.187541 | I92: =+I79-I90 -> 18.642229 | J92: =+J79-J90 -> 19.108285 | K92: =+K79-K90 -> 19.585992 | L92: =+L79-L90 -> 20.075642 | M92: =+M79-M90 -> 20.577533 | N92: =+N79-N90 -> 21.091971 | O92: =+O79-O90 -> 21.61927 | ... AF92: =+AF79-AF90 -> 32.896277
A94: Start-up Opex Reserve | G94: =-H90*0.5 -> -1.8091762
A96: Pre-Tax Unlevered Cash Flow | C96: $mm | E96: =-E35 -> -12.6 | F96: =-F35 -> -50.4 | G96: =G94-G35 -> -64.809176 | H96: =+H92 -> 18.187541 | I96: =+I92 -> 18.642229 | J96: =+J92 -> 19.108285 | K96: =+K92 -> 19.585992 | L96: =+L92 -> 20.075642 | M96: =+M92 -> 20.577533 | N96: =+N92 -> 21.091971 | O96: =+O92 -> 21.61927 | ... AF96: =+AF92 -> 32.896277
A98: Pre-Tax Unlevered IRR | C98: % | E98: =+IRR(E96:AF96) -> 0.14789651
A99: NPV 10 | C99: $mm | E99: =+NPV(0.1,E96:AF96) -> 49.219162
A101: Finance Plan
A103: Construction Debt Program
A104: Construction Debt Term | C104: Yrs | D104: =+E42 -> 3
A105: Construction Debt Rate | C105: % | D105: =+E43 -> 0.05
A106: Construction Debt Leverage | C106: % | D106: =+E44 -> 0.5
A108: S Curve-Construction Expenditure
A109: S Curve | C109: Yr | E109: Yr1 | F109: Yr2 | G109: Yr3 | I109: Total
A110: S Curve | C110: % | E110: =+E34 -> 0.1 | F110: =+F34 -> 0.4 | G110: 0.5 | I110: =+SUM(E110:G110) -> 1
A111: S Curve | C111: $mm | E111: =+E35 -> 12.6 | F111: =+F35 -> 50.4 | G111: =+G35 -> 63 | I111: =+SUM(E111:G111) -> 126
A113: Construction Finance | E113: Yr1 | F113: Yr2 | G113: Yr3
A114: Constuction Debt BOY | C114: $mm | E114: 0 | F114: =+E119 -> 6.4575 | G114: =+F119 -> 32.610375
A115: Construction Debt Add | C115: $mm | E115: =+E111*$D$106 -> 6.3 | F115: =+F111*$D$106 -> 25.2 | G115: =+G111*$D$106 -> 31.5
A116: Construction Debt EOY b4 IDC | C116: $mm | E116: =+E114+E115 -> 6.3 | F116: =+F114+F115 -> 31.6575 | G116: =+G114+G115 -> 64.110375
A117: Construction Debt Ave | C117: $mm | E117: =+(E114+E116)/2 -> 3.15 | F117: =+(F114+F116)/2 -> 19.0575 | G117: =+(G114+G116)/2 -> 48.360375
A118: Interest During Construction (IDC) | C118: $mm | E118: =+E117*$D$105 -> 0.1575 | F118: =+F117*$D$105 -> 0.952875 | G118: =+G117*$D$105 -> 2.4180188
A119: Consturction Debt EOY a IDC | C119: $mm | E119: =+E116+E118 -> 6.4575 | F119: =+F116+F118 -> 32.610375 | G119: =+G116+G118 -> 66.528394
E121: Yr1 | F121: Yr2 | G121: Yr3
A122: Construction Equity per Year | C122: $mm | E122: =+E111-E115 -> 6.3 | F122: =+F111-F115 -> 25.2 | G122: =+G111-G115 -> 31.5
A123: Construction Equity Total | C123: $mm | E123: =+E122 -> 6.3 | F123: =+E123+F122 -> 31.5 | G123: =+F123+G122 -> 63
A125: Final Construction Capital Structure | E125: Yr1 | F125: Yr2 | G125: Yr3
A126: Debt @ End of Construction Loan | C126: $mm | E126: =+E119 -> 6.4575 | F126: =+F119 -> 32.610375 | G126: =+G119 -> 66.528394
A127: Equity @ End of Construction Loan | C127: $mm | E127: =+E122 -> 6.3 | F127: =+F123 -> 31.5 | G127: =+G123 -> 63
A128: Total Capital | C128: $mm | E128: =SUM(E126:E127) -> 12.7575 | F128: =SUM(F126:F127) -> 64.110375 | G128: =SUM(G126:G127) -> 129.52839
A130: Take-Out Finance Program
A132: Take-Out Loan Program
A133: Take-Out Debt Term | C133: Yrs | D133: =+E46 -> 15
A134: Take-Out Debt Rate | C134: % | D134: =+E47 -> 0.065
A135: Take-Out Debt Leverage | C135: % | D135: =+E48 -> 0.59555421
A137: Take-Out Capital Structure
...

Sheet Case Study Base Data
A1: Column1 | B1: Column2 | C1: Column3 | D1: Column4 | E1: Column5 | F1: Column6 | G1: Column7 | H1: Column8 | I1: Column9 | J1: Column10 | K1: Column11 | L1: Column12
A2: Case Study Base Data | L2: Class Case Study
J3: Natural Gas | L3: Natural Gas
A4: Technology | D4: Units | F4: Solar | H4: Wind | J4: NG CT | L4: NG CCGT
A6: Capacity Units | D6: MW | F6: MW | H6: MW | J6: MW | L6: MW
A7: Capacity | F7: 80 | H7: 80 | J7: 100 | L7: 700
A8: Location | F8: Arizona | H8: Texas | J8: Texas | L8: Texas
A9: Capital Cost: Note 1 | D9: $/kw | F9: 1000 | H9: 1500 | J9: 1000 | L9: 1000
A10: Heat Rate/Fuel Rate | D10: btu/kwh | F10: 0 | H10: 0 | J10: 9600 | L10: 6400
A11: Fixed O&M | D11: $/kw/yr | F11: 13 | H11: 42 | J11: 12 | L11: 11
A12: Variable O&M | D12: $/mwh | F12: 0 | H12: 0 | J12: 7 | L12: 3
A13: Lead Time | D13: Years | F13: 3 | H13: 3 | J13: 3 | L13: 3
A14: S Curve Year One | B14: Yr 1 | D14: % | F14: 0.1 | H14: 0.1 | J14: 0.2 | L14: 0.2
A15: S Curve Year Two | B15: Yr 2 | D15: % | F15: 0.2 | H15: 0.4 | J15: 0.6 | L15: 0.7
A16: S Curve Year Three | B16: Yr 3 | D16: % | F16: 0.7 | H16: 0.5 | J16: 0.2 | L16: 0.1
A17: Capacity Factor: Note 2 | D17: % | F17: 0.24 | H17: 0.4 | J17: 0.2 | L17: 0.9
A18: Fuel Costs: Note 3 | D18: $/mmbtu | F18: 0 | H18: 0 | J18: 4.5 | L18: 4.5
A19: Economic Life | D19: Years | F19: 25 | H19: 25 | J19: 25 | L19: 25
A20: Tax Depreciation | D20: Note 3 | F20: 5 | H20: 5 | J20: 15 | L20: 15
A21: Price Inflation Rate | D21: % | F21: 0.025 | H21: 0.025 | J21: 0.025 | L21: 0.025
A22: Cost Inflation Rate | D22: % | F22: 0.025 | H22: 0.025 | J22: 0.025 | L22: 0.025
A23: Tax Credit/ | D23: % | F23: 0.3 | H23: 0.3 | J23: 0 | L23: 0
A24: Tax Rate | D24: Federal | F24: 0.21 | H24: 0.21 | J24: 0.21 | L24: 0.21
A25: Construction Debt Term | D25: Yrs | F25: 3 | H25: 3 | J25: 3 | L25: 3
A26: Construction Debt Rate | D26: % | F26: 0.05 | H26: 0.05 | J26: 0.05 | L26: 0.05
A27: Construction Debt Leverage | D27: % | F27: 0.5 | H27: 0.5 | J27: 0.5 | L27: 0.5
A28: Take-Out Debt Term | D28: Yrs | F28: 15 | H28: 15 | J28: 15 | L28: 15
... A31: Development Fee | D31: % | F31: 0.05 | H31: 0.05 | J31: 0.05 | L31: 0.05
A33: Note 1 | B33: EPC Cost including contingency but excluding the Development Fee ----- Start of S Curve 2025
A34: Note 2 | B34: Tucson Az Use PV Watts to check the capacity factor
A35: Note 3 | B35: Solar, Wind | D35: MACRS | E35: 5 | F35: Yr 1 | G35: Yr 2 | H35: Yr 3 | I35: Yr 4 | J35: Yr 5 | K35: Yr 6
F36: 0.2 | G36: 0.32 | H36: 0.192 | I36: 0.1152 | J36: 0.1152 | K36: 0.0576
B37: GT, CCGT | D37: MACRS | E37: 15 | F37: Yr 1 | G37: Yr 2 | H37: Yr 3 | I37: Yr 4 | J37: Yr 5 | K37: Yr 6
F38: 0.05 | G38: 0.095 | H38: 0.0855 | I38: 0.077 | J38: 0.0693 | K38: 0.0623
F39: Yr 11 | G39: Yr 12 | H39: Yr 13 | I39: Yr 14 | J39: Yr 15 | K39: Yr 16
F40: 0.0591 | G40: 0.059 | H40: 0.0591 | I40: 0.059 | J40: 0.0591 | K40: 0.0295
